DrugAutoML/__init__.py
DrugAutoML/data_preprocess.py
DrugAutoML/data_split.py
DrugAutoML/explainability.py
DrugAutoML/featurization.py
DrugAutoML/model_finalization.py
DrugAutoML/model_selection.py
DrugAutoML/pipeline.py
DrugAutoML/prediction.py
drugautoml-0.1.4.dist-info/METADATA
drugautoml-0.1.4.dist-info/WHEEL
drugautoml-0.1.4.dist-info/top_level.txt
drugautoml-0.1.4.dist-info/RECORD
