Metadata-Version: 2.4
Name: DrugAutoML
Version: 0.1.4
Summary: Automated Machine Learning pipeline for bioactivity prediction using molecular fingerprints
Home-page: https://github.com/aycapmkcu/DrugAutoML
Author: Your Name
Author-email: ayca.beyhan@msu.edu.tr
Classifier: Programming Language :: Python :: 3
Classifier: License :: OSI Approved :: MIT License
Classifier: Operating System :: OS Independent
Requires-Python: >=3.8
Requires-Dist: pandas
Requires-Dist: numpy
Requires-Dist: scikit-learn
Requires-Dist: matplotlib
Requires-Dist: seaborn
Requires-Dist: optuna
Requires-Dist: xgboost
Requires-Dist: lightgbm
Requires-Dist: joblib
Requires-Dist: scipy
Requires-Dist: rdkit-pypi
Requires-Dist: shap
Dynamic: author
Dynamic: author-email
Dynamic: classifier
Dynamic: description
Dynamic: description-content-type
Dynamic: home-page
Dynamic: requires-dist
Dynamic: requires-python
Dynamic: summary
